hashstate-0.2.1.dist-info/WHEEL
hashstate-0.2.1.dist-info/METADATA
hashstate-0.2.1.dist-info/top_level.txt
hashstate-0.2.1.dist-info/RECORD
hashstate/__init__.py
hashstate/_hashstate.cpython-34m.so
hashstate/.libs/libk5crypto-622ef25b.so.3.1
hashstate/.libs/libgssapi_krb5-174f8956.so.2.2
hashstate/.libs/libkrb5support-d7ce89d4.so.0.1
hashstate/.libs/libcom_err-beb60336.so.2.1
hashstate/.libs/libssl-a65b360f.so.0.9.8e
hashstate/.libs/libcrypto-de69073a.so.0.9.8e
hashstate/.libs/libkrb5-fb0d2caa.so.3.3
hashstate/.libs/libselinux-cf8f9094.so.1
hashstate/.libs/libz-a147dcb0.so.1.2.3
hashstate/.libs/libsepol-b4f5b513.so.1
hashstate/.libs/libkeyutils-1-ff31573b.2.so
