Metadata-Version: 2.1
Name: hashstate
Version: 0.2.1
Summary: Serializable hash objects
Home-page: https://github.com/zachmullen/hashstate
License: UNKNOWN
Platform: UNKNOWN
